Time_Machine/GUI_AgeDating.py
Time_Machine/GUI_ImageAnalysis.py
Time_Machine/Image_Process.py
Time_Machine/Inversion_Class.py
Time_Machine/Multi_Stage.py
Time_Machine/Profile_Analysis.py
Time_Machine/__init__.py
Time_Machine/__main__.py
Time_Machine/Data/Burial_data_example.txt
Time_Machine/Data/LN_Calibration_880_20s.tif
Time_Machine/Data/LN_Calibration_880_20s_after_IRSL.tif
Time_Machine/Data/LN_Calibration_955_20s.tif
Time_Machine/Data/LN_Calibration_955_20s_after_IRSL.tif
Time_Machine/Data/LN_Calibration_IRSL_10s_20_frames.tif
"Time_Machine/Data/LN_Calibration_optical_0,01s.tif"
Time_Machine/Data/LN_Dating_880_20s.tif
Time_Machine/Data/LN_Dating_880_20s_after_IRSL.tif
Time_Machine/Data/LN_Dating_955_20s.tif
Time_Machine/Data/LN_Dating_955_20s_after_IRSL.tif
Time_Machine/Data/LN_Dating_IRSL_3s_67_frames.tif
"Time_Machine/Data/LN_Dating_optical_0,01s.tif"
Time_Machine/Data/TN_Calibration_880_20s.tif
Time_Machine/Data/TN_Calibration_955_20s.tif
Time_Machine/Data/TN_Calibration_IRSL_10s_20_frames.tif
"Time_Machine/Data/TN_Calibration_optical_0,01s.tif"
Time_Machine/Data/TN_Dating_880_20s.tif
Time_Machine/Data/TN_Dating_955_20s.tif
Time_Machine/Data/TN_Dating_IRSL_3s_67_frames.tif
"Time_Machine/Data/TN_Dating_optical_0,01s.tif"
Time_Machine/Data/Trine_profile.txt
My_This_is_the_machine-0.0.7.dist-info/LICENSE
My_This_is_the_machine-0.0.7.dist-info/METADATA
My_This_is_the_machine-0.0.7.dist-info/WHEEL
My_This_is_the_machine-0.0.7.dist-info/top_level.txt
My_This_is_the_machine-0.0.7.dist-info/RECORD
