Metadata-Version: 2.1
Name: My-This-is-the-machine
Version: 0.0.7
Summary: A small example package
Author-email: This is me <gorosti.mantxo@gmail.com>
Project-URL: Homepage, https://github.com/pypa/sampleproject
Project-URL: Bug Tracker, https://github.com/pypa/sampleproject/issues
Classifier: Programming Language :: Python :: 3
Classifier: License :: OSI Approved :: MIT License
Classifier: Operating System :: OS Independent
Requires-Python: >=3.7
License-File: LICENSE
Requires-Dist: numpy
Requires-Dist: pandas
Requires-Dist: matplotlib
Requires-Dist: scipy
Requires-Dist: opencv-python
Requires-Dist: imreg
Requires-Dist: tifffile
